wodonga/__init__.py
wodonga/__main__.py
wodonga/service.py
wodonga/service_loader.py
wodonga/service_test.py
wodonga/tcp.py
wodonga-0.1.dist-info/LICENSE.md
wodonga-0.1.dist-info/WHEEL
wodonga-0.1.dist-info/METADATA
wodonga-0.1.dist-info/RECORD
