Metadata-Version: 2.1
Name: wodonga
Version: 0.1
Summary: 
Author: Leigh Brenecki
Author-email: l@leigh.net.au
Requires-Python: >=3.8,<4.0
Classifier: Programming Language :: Python :: 3
Classifier: Programming Language :: Python :: 3.8
Requires-Dist: appdirs (>=1.4.4,<2.0.0)
Requires-Dist: cityhash (>=0.2.3,<0.3.0)
Requires-Dist: pytest (>=5.4.2,<6.0.0)
Requires-Dist: pytest-trio (>=0.5.2,<0.6.0)
Requires-Dist: structlog (>=20.1.0,<21.0.0)
Requires-Dist: tomlkit (>=0.6.0,<0.7.0)
Requires-Dist: trio (>=0.15.1,<0.16.0)
